{
  "meta": {
    "catecory": "car",
    "shape_id": "drivaer_127"
  },
  "part": [
    {
      "name": "body_shell",
      "dfn": 1,
      "dfn_fa": 0,
      "mesh": "car_drivaer_127_1.ply",
      "bbx": [
        [
          -0.868733,
          -1.09907,
          -0.17211
        ],
        [
          3.69673,
          1.09907,
          1.03818
        ]
      ],
      "joint_data_origin": [
        0,
        0,
        0
      ],
      "joint_data_direction": [
        0,
        0,
        0
      ],
      "limit": [
        0.0,
        0.0,
        0.0,
        0.0
      ]
    },
    {
      "name": "wheel_front_left",
      "dfn": 2,
      "dfn_fa": 1,
      "mesh": "car_drivaer_127_2.ply",
      "bbx": [
        [
          -0.311486,
          -0.94024,
          -0.319646
        ],
        [
          0.32549,
          -0.695358,
          0.318301
        ]
      ],
      "joint_data_origin": [
        0.006949471251921381,
        -0.8246990464850229,
        -0.0004473468586818106
      ],
      "joint_data_direction": [
        0.0,
        1.0,
        0.0
      ],
      "limit": [
        0.0,
        0.0,
        0.0,
        6.283185307179586
      ]
    },
    {
      "name": "wheel_front_right",
      "dfn": 3,
      "dfn_fa": 1,
      "mesh": "car_drivaer_127_3.ply",
      "bbx": [
        [
          -0.311486,
          0.695358,
          -0.319612
        ],
        [
          0.32549,
          0.94024,
          0.318301
        ]
      ],
      "joint_data_origin": [
        0.006947055777516626,
        0.824699294639451,
        -0.0004468248480288759
      ],
      "joint_data_direction": [
        0.0,
        1.0,
        0.0
      ],
      "limit": [
        0.0,
        0.0,
        0.0,
        6.283185307179586
      ]
    },
    {
      "name": "wheel_rear_left",
      "dfn": 4,
      "dfn_fa": 1,
      "mesh": "car_drivaer_127_4.ply",
      "bbx": [
        [
          2.45764,
          -0.943958,
          -0.319602
        ],
        [
          3.09463,
          -0.69866,
          0.318578
        ]
      ],
      "joint_data_origin": [
        2.77621049235159,
        -0.8279138828570031,
        -0.0002688907962753187
      ],
      "joint_data_direction": [
        0.0,
        1.0,
        0.0
      ],
      "limit": [
        0.0,
        0.0,
        0.0,
        6.283185307179586
      ]
    },
    {
      "name": "wheel_rear_right",
      "dfn": 5,
      "dfn_fa": 1,
      "mesh": "car_drivaer_127_5.ply",
      "bbx": [
        [
          2.45764,
          0.69866,
          -0.3196
        ],
        [
          3.09463,
          0.943958,
          0.318578
        ]
      ],
      "joint_data_origin": [
        2.7762112394513685,
        0.8279142415729104,
        -0.0002694640963979355
      ],
      "joint_data_direction": [
        0.0,
        1.0,
        0.0
      ],
      "limit": [
        0.0,
        0.0,
        0.0,
        6.283185307179586
      ]
    }
  ]
}