{
  "meta": {
    "catecory": "car",
    "shape_id": "drivaer_440"
  },
  "part": [
    {
      "name": "body_shell",
      "dfn": 1,
      "dfn_fa": 0,
      "mesh": "car_drivaer_440_1.ply",
      "bbx": [
        [
          -0.828009,
          -0.972833,
          -0.203199
        ],
        [
          3.94431,
          0.972833,
          1.05469
        ]
      ],
      "joint_data_origin": [
        0,
        0,
        0
      ],
      "joint_data_direction": [
        0,
        0,
        0
      ],
      "limit": [
        0.0,
        0.0,
        0.0,
        0.0
      ]
    },
    {
      "name": "wheel_front_left",
      "dfn": 2,
      "dfn_fa": 1,
      "mesh": "car_drivaer_440_2.ply",
      "bbx": [
        [
          -0.311487,
          -0.83362,
          -0.319644
        ],
        [
          0.325488,
          -0.616949,
          0.31843
        ]
      ],
      "joint_data_origin": [
        0.007042115965842429,
        -0.731713362872929,
        -0.0003223947690877064
      ],
      "joint_data_direction": [
        0.0,
        1.0,
        0.0
      ],
      "limit": [
        0.0,
        0.0,
        0.0,
        6.283185307179586
      ]
    },
    {
      "name": "wheel_front_right",
      "dfn": 3,
      "dfn_fa": 1,
      "mesh": "car_drivaer_440_3.ply",
      "bbx": [
        [
          -0.311487,
          0.616949,
          -0.319607
        ],
        [
          0.325488,
          0.83362,
          0.31843
        ]
      ],
      "joint_data_origin": [
        0.007039365433671879,
        0.7317130082162844,
        -0.0003217705599630218
      ],
      "joint_data_direction": [
        0.0,
        1.0,
        0.0
      ],
      "limit": [
        0.0,
        0.0,
        0.0,
        6.283185307179586
      ]
    },
    {
      "name": "wheel_rear_left",
      "dfn": 4,
      "dfn_fa": 1,
      "mesh": "car_drivaer_440_4.ply",
      "bbx": [
        [
          2.63186,
          -0.836846,
          -0.319614
        ],
        [
          3.26878,
          -0.619335,
          0.318617
        ]
      ],
      "joint_data_origin": [
        2.9502554268322396,
        -0.734656830841332,
        -0.00023697919171368966
      ],
      "joint_data_direction": [
        0.0,
        1.0,
        0.0
      ],
      "limit": [
        0.0,
        0.0,
        0.0,
        6.283185307179586
      ]
    },
    {
      "name": "wheel_rear_right",
      "dfn": 5,
      "dfn_fa": 1,
      "mesh": "car_drivaer_440_5.ply",
      "bbx": [
        [
          2.63186,
          0.619335,
          -0.319607
        ],
        [
          3.26878,
          0.836846,
          0.318617
        ]
      ],
      "joint_data_origin": [
        2.950255926817126,
        0.7346574256218437,
        -0.00023705368431885918
      ],
      "joint_data_direction": [
        0.0,
        1.0,
        0.0
      ],
      "limit": [
        0.0,
        0.0,
        0.0,
        6.283185307179586
      ]
    }
  ]
}