{
  "meta": {
    "catecory": "car",
    "shape_id": "drivaer_13"
  },
  "part": [
    {
      "name": "body_shell",
      "dfn": 1,
      "dfn_fa": 0,
      "mesh": "car_drivaer_13_1.ply",
      "bbx": [
        [
          -0.887001,
          -0.98418,
          -0.166816
        ],
        [
          3.65295,
          0.98418,
          1.11033
        ]
      ],
      "joint_data_origin": [
        0,
        0,
        0
      ],
      "joint_data_direction": [
        0,
        0,
        0
      ],
      "limit": [
        0.0,
        0.0,
        0.0,
        0.0
      ]
    },
    {
      "name": "wheel_front_left",
      "dfn": 2,
      "dfn_fa": 1,
      "mesh": "car_drivaer_13_2.ply",
      "bbx": [
        [
          -0.311483,
          -0.842544,
          -0.319612
        ],
        [
          0.3255,
          -0.62377,
          0.318349
        ]
      ],
      "joint_data_origin": [
        0.007044358745972817,
        -0.7396478521053939,
        -0.000187392186644352
      ],
      "joint_data_direction": [
        0.0,
        1.0,
        0.0
      ],
      "limit": [
        0.0,
        0.0,
        0.0,
        6.283185307179586
      ]
    },
    {
      "name": "wheel_front_right",
      "dfn": 3,
      "dfn_fa": 1,
      "mesh": "car_drivaer_13_3.ply",
      "bbx": [
        [
          -0.311483,
          0.62377,
          -0.319574
        ],
        [
          0.3255,
          0.842544,
          0.318349
        ]
      ],
      "joint_data_origin": [
        0.0070438829099244964,
        0.7396477406864693,
        -0.00018638177158091266
      ],
      "joint_data_direction": [
        0.0,
        1.0,
        0.0
      ],
      "limit": [
        0.0,
        0.0,
        0.0,
        6.283185307179586
      ]
    },
    {
      "name": "wheel_rear_left",
      "dfn": 4,
      "dfn_fa": 1,
      "mesh": "car_drivaer_13_4.ply",
      "bbx": [
        [
          2.33575,
          -0.845552,
          -0.31963
        ],
        [
          2.97255,
          -0.623452,
          0.318425
        ]
      ],
      "joint_data_origin": [
        2.654089566179019,
        -0.7418419533069546,
        -0.0001525066351882914
      ],
      "joint_data_direction": [
        0.0,
        1.0,
        0.0
      ],
      "limit": [
        0.0,
        0.0,
        0.0,
        6.283185307179586
      ]
    },
    {
      "name": "wheel_rear_right",
      "dfn": 5,
      "dfn_fa": 1,
      "mesh": "car_drivaer_13_5.ply",
      "bbx": [
        [
          2.33575,
          0.623452,
          -0.31963
        ],
        [
          2.97255,
          0.845552,
          0.318425
        ]
      ],
      "joint_data_origin": [
        2.654089980555267,
        0.7418416939874511,
        -0.0001513838990156251
      ],
      "joint_data_direction": [
        0.0,
        1.0,
        0.0
      ],
      "limit": [
        0.0,
        0.0,
        0.0,
        6.283185307179586
      ]
    }
  ]
}