{
  "meta": {
    "catecory": "car",
    "shape_id": "drivaer_286"
  },
  "part": [
    {
      "name": "body_shell",
      "dfn": 1,
      "dfn_fa": 0,
      "mesh": "car_drivaer_286_1.ply",
      "bbx": [
        [
          -0.909473,
          -1.03947,
          -0.149351
        ],
        [
          3.91127,
          1.03947,
          1.10606
        ]
      ],
      "joint_data_origin": [
        0,
        0,
        0
      ],
      "joint_data_direction": [
        0,
        0,
        0
      ],
      "limit": [
        0.0,
        0.0,
        0.0,
        0.0
      ]
    },
    {
      "name": "wheel_front_left",
      "dfn": 2,
      "dfn_fa": 1,
      "mesh": "car_drivaer_286_2.ply",
      "bbx": [
        [
          -0.311485,
          -0.919981,
          -0.319647
        ],
        [
          0.325492,
          -0.680816,
          0.318187
        ]
      ],
      "joint_data_origin": [
        0.006969383976599587,
        -0.8072491523586772,
        -0.00048239266896159754
      ],
      "joint_data_direction": [
        0.0,
        1.0,
        0.0
      ],
      "limit": [
        0.0,
        0.0,
        0.0,
        6.283185307179586
      ]
    },
    {
      "name": "wheel_front_right",
      "dfn": 3,
      "dfn_fa": 1,
      "mesh": "car_drivaer_286_3.ply",
      "bbx": [
        [
          -0.311485,
          0.680816,
          -0.319613
        ],
        [
          0.325492,
          0.919981,
          0.318187
        ]
      ],
      "joint_data_origin": [
        0.006968095110705554,
        0.8072488973234395,
        -0.00048176248899964644
      ],
      "joint_data_direction": [
        0.0,
        1.0,
        0.0
      ],
      "limit": [
        0.0,
        0.0,
        0.0,
        6.283185307179586
      ]
    },
    {
      "name": "wheel_rear_left",
      "dfn": 4,
      "dfn_fa": 1,
      "mesh": "car_drivaer_286_4.ply",
      "bbx": [
        [
          2.54904,
          -0.9235,
          -0.319607
        ],
        [
          3.18584,
          -0.68202,
          0.318525
        ]
      ],
      "joint_data_origin": [
        2.8674130294211824,
        -0.8098696125810223,
        -0.0002752664535291226
      ],
      "joint_data_direction": [
        0.0,
        1.0,
        0.0
      ],
      "limit": [
        0.0,
        0.0,
        0.0,
        6.283185307179586
      ]
    },
    {
      "name": "wheel_rear_right",
      "dfn": 5,
      "dfn_fa": 1,
      "mesh": "car_drivaer_286_5.ply",
      "bbx": [
        [
          2.54904,
          0.68202,
          -0.319603
        ],
        [
          3.18584,
          0.9235,
          0.318525
        ]
      ],
      "joint_data_origin": [
        2.867410684523349,
        0.8098695852416239,
        -0.00027571366785757184
      ],
      "joint_data_direction": [
        0.0,
        1.0,
        0.0
      ],
      "limit": [
        0.0,
        0.0,
        0.0,
        6.283185307179586
      ]
    }
  ]
}