{
  "meta": {
    "catecory": "car",
    "shape_id": "drivaer_38"
  },
  "part": [
    {
      "name": "body_shell",
      "dfn": 1,
      "dfn_fa": 0,
      "mesh": "car_drivaer_38_1.ply",
      "bbx": [
        [
          -0.746071,
          -1.04225,
          -0.214937
        ],
        [
          3.76137,
          1.04225,
          1.133
        ]
      ],
      "joint_data_origin": [
        0,
        0,
        0
      ],
      "joint_data_direction": [
        0,
        0,
        0
      ],
      "limit": [
        0.0,
        0.0,
        0.0,
        0.0
      ]
    },
    {
      "name": "wheel_front_left",
      "dfn": 2,
      "dfn_fa": 1,
      "mesh": "car_drivaer_38_2.ply",
      "bbx": [
        [
          -0.311487,
          -0.891658,
          -0.319617
        ],
        [
          0.32549,
          -0.660464,
          0.318758
        ]
      ],
      "joint_data_origin": [
        0.00698501438069563,
        -0.7828006832188192,
        -9.652285804242372e-05
      ],
      "joint_data_direction": [
        0.0,
        1.0,
        0.0
      ],
      "limit": [
        0.0,
        0.0,
        0.0,
        6.283185307179586
      ]
    },
    {
      "name": "wheel_front_right",
      "dfn": 3,
      "dfn_fa": 1,
      "mesh": "car_drivaer_38_3.ply",
      "bbx": [
        [
          -0.311487,
          0.660464,
          -0.319579
        ],
        [
          0.32549,
          0.891658,
          0.318758
        ]
      ],
      "joint_data_origin": [
        0.006982862691832243,
        0.7828009359720199,
        -9.322248572625195e-05
      ],
      "joint_data_direction": [
        0.0,
        1.0,
        0.0
      ],
      "limit": [
        0.0,
        0.0,
        0.0,
        6.283185307179586
      ]
    },
    {
      "name": "wheel_rear_left",
      "dfn": 4,
      "dfn_fa": 1,
      "mesh": "car_drivaer_38_4.ply",
      "bbx": [
        [
          2.51701,
          -0.894975,
          -0.319605
        ],
        [
          3.1539,
          -0.662021,
          0.318616
        ]
      ],
      "joint_data_origin": [
        2.8354534259126183,
        -0.7855838066583614,
        -0.00020037110350650355
      ],
      "joint_data_direction": [
        0.0,
        1.0,
        0.0
      ],
      "limit": [
        0.0,
        0.0,
        0.0,
        6.283185307179586
      ]
    },
    {
      "name": "wheel_rear_right",
      "dfn": 5,
      "dfn_fa": 1,
      "mesh": "car_drivaer_38_5.ply",
      "bbx": [
        [
          2.51701,
          0.662021,
          -0.319601
        ],
        [
          3.1539,
          0.894975,
          0.318616
        ]
      ],
      "joint_data_origin": [
        2.8354505930174883,
        0.7855840624259924,
        -0.00020170317014954234
      ],
      "joint_data_direction": [
        0.0,
        1.0,
        0.0
      ],
      "limit": [
        0.0,
        0.0,
        0.0,
        6.283185307179586
      ]
    }
  ]
}