{
  "meta": {
    "catecory": "car",
    "shape_id": "drivaer_405"
  },
  "part": [
    {
      "name": "body_shell",
      "dfn": 1,
      "dfn_fa": 0,
      "mesh": "car_drivaer_405_1.ply",
      "bbx": [
        [
          -0.760952,
          -1.01557,
          -0.17864
        ],
        [
          3.62528,
          1.01557,
          1.09796
        ]
      ],
      "joint_data_origin": [
        0,
        0,
        0
      ],
      "joint_data_direction": [
        0,
        0,
        0
      ],
      "limit": [
        0.0,
        0.0,
        0.0,
        0.0
      ]
    },
    {
      "name": "wheel_front_left",
      "dfn": 2,
      "dfn_fa": 1,
      "mesh": "car_drivaer_405_2.ply",
      "bbx": [
        [
          -0.31149,
          -0.865042,
          -0.319652
        ],
        [
          0.32548,
          -0.640968,
          0.318611
        ]
      ],
      "joint_data_origin": [
        0.007000912933118787,
        -0.7596397637359003,
        -0.0003209828333069178
      ],
      "joint_data_direction": [
        0.0,
        1.0,
        0.0
      ],
      "limit": [
        0.0,
        0.0,
        0.0,
        6.283185307179586
      ]
    },
    {
      "name": "wheel_front_right",
      "dfn": 3,
      "dfn_fa": 1,
      "mesh": "car_drivaer_405_3.ply",
      "bbx": [
        [
          -0.31149,
          0.640968,
          -0.319618
        ],
        [
          0.32548,
          0.865042,
          0.318611
        ]
      ],
      "joint_data_origin": [
        0.007001684175155296,
        0.7596396291212892,
        -0.00031996521159202983
      ],
      "joint_data_direction": [
        0.0,
        1.0,
        0.0
      ],
      "limit": [
        0.0,
        0.0,
        0.0,
        6.283185307179586
      ]
    },
    {
      "name": "wheel_rear_left",
      "dfn": 4,
      "dfn_fa": 1,
      "mesh": "car_drivaer_405_4.ply",
      "bbx": [
        [
          2.32559,
          -0.868106,
          -0.319629
        ],
        [
          2.96245,
          -0.641661,
          0.318428
        ]
      ],
      "joint_data_origin": [
        2.644005884795104,
        -0.7621384628472738,
        -0.00018822684209245653
      ],
      "joint_data_direction": [
        0.0,
        1.0,
        0.0
      ],
      "limit": [
        0.0,
        0.0,
        0.0,
        6.283185307179586
      ]
    },
    {
      "name": "wheel_rear_right",
      "dfn": 5,
      "dfn_fa": 1,
      "mesh": "car_drivaer_405_5.ply",
      "bbx": [
        [
          2.32559,
          0.641661,
          -0.319591
        ],
        [
          2.96245,
          0.868106,
          0.318428
        ]
      ],
      "joint_data_origin": [
        2.6440055076742737,
        0.7621384791980207,
        -0.00018708305511996233
      ],
      "joint_data_direction": [
        0.0,
        1.0,
        0.0
      ],
      "limit": [
        0.0,
        0.0,
        0.0,
        6.283185307179586
      ]
    }
  ]
}